svgrepo_dl/__init__.py
svgrepo_dl/__main__.py
svg_repo_dl-0.0.0.dist-info/METADATA
svg_repo_dl-0.0.0.dist-info/WHEEL
svg_repo_dl-0.0.0.dist-info/top_level.txt
svg_repo_dl-0.0.0.dist-info/RECORD
