Metadata-Version: 2.1
Name: svg-repo-dl
Version: 0.0.0
Summary: SVGrepo-dl is a library & command-line tool for downloading SVG icons and illustrations from 'svgrepo.com'.
Author: Duckling Dean
Author-email: duckling.dean@proton.me
